LICENSE
MANIFEST.in
README.rst
requirements-docs.txt
requirements-test.txt
requirements.txt
setup.cfg
setup.py
txt2xls.1
src/txt2xls/__init__.py
src/txt2xls/args.py
src/txt2xls/compat.py
src/txt2xls/conf.py
src/txt2xls/config.spec
src/txt2xls/console.py
src/txt2xls.egg-info/PKG-INFO
src/txt2xls.egg-info/SOURCES.txt
src/txt2xls.egg-info/dependency_links.txt
src/txt2xls.egg-info/entry_points.txt
src/txt2xls.egg-info/requires.txt
src/txt2xls.egg-info/top_level.txt
src/txt2xls.egg-info/zip-safe
src/txt2xls/function/__init__.py
src/txt2xls/function/builtin/__init__.py
src/txt2xls/function/builtin/baseline_function.py
src/txt2xls/function/builtin/classify_function.py
src/txt2xls/function/builtin/unite_function.py
src/txt2xls/reader/__init__.py
src/txt2xls/writer/__init__.py
src/txt2xls/writer/utils.py