Metadata-Version: 1.1
Name: txt2xls
Version: 0.2.2
Summary: Convert raw text data files into a single excel file.
Home-page: https://github.com/lambdalisue/txt2xls
Author: Alisue
Author-email: lambdalisue@hashnote.net
License: MIT
Download-URL: https://github.com/lambdalisue/txt2xls/tarball/master
Keywords: raw text data convert excel xls
Platform: UNKNOWN
Classifier: Development Status :: 3 - Alpha
Classifier: Intended Audience :: Developers
Classifier: License :: OSI Approved :: MIT License
Classifier: Programming Language :: Python
Classifier: Programming Language :: Python :: 2.6
Classifier: Programming Language :: Python :: 2.7
